hafersack/__init__.py
hafersack/py.typed
hafersack-0.1.0.dist-info/WHEEL
hafersack-0.1.0.dist-info/METADATA
hafersack-0.1.0.dist-info/RECORD
