Metadata-Version: 2.3
Name: hafersack
Version: 0.1.0
Summary: Store and retrieve metadata in any object.
Requires-Python: >=3.13
